pip_negotiator/__init__.py
pip_negotiator/pip_negotiator.py
pip_negotiator/commands/__init__.py
pip_negotiator/commands/base.py
pip_negotiator/commands/pip.py
pip_negotiator/commands/pipcompile.py
pip_negotiator/requirements/__init__.py
pip_negotiator/requirements/requirements.py
pip_negotiator-1.4.1.dist-info/AUTHORS.rst
pip_negotiator-1.4.1.dist-info/LICENSE
pip_negotiator-1.4.1.dist-info/METADATA
pip_negotiator-1.4.1.dist-info/WHEEL
pip_negotiator-1.4.1.dist-info/entry_points.txt
pip_negotiator-1.4.1.dist-info/top_level.txt
pip_negotiator-1.4.1.dist-info/RECORD
