Metadata-Version: 2.1
Name: pip-negotiator
Version: 1.4.1
Summary: A simple tool with the goal to  keep your pip packages without conflicts
Home-page: https://github.com/gchiesa/pip_negotiator
Author: Giuseppe Chiesa
Author-email: mail@giuseppechiesa.it
License: BSD license
Keywords: pip_negotiator
Platform: UNKNOWN
Classifier: Development Status :: 4 - Beta
Classifier: Intended Audience :: Developers
Classifier: License :: OSI Approved :: BSD License
Classifier: Natural Language :: English
Classifier: Programming Language :: Python :: 2.7
Classifier: Programming Language :: Python :: 3.7
Requires-Dist: pip-tools (==3.5.0)
Requires-Dist: pip (==19.0.3)
Requires-Dist: six
